systembridgewindowssensors/__init__.py
systembridgewindowssensors/_version.py
systembridgewindowssensors/bin/HidSharp.dll
systembridgewindowssensors/bin/LibreHardwareMonitorLib.dll
systembridgewindowssensors/bin/Newtonsoft.Json.dll
systembridgewindowssensors/bin/NvAPIWrapper.dll
systembridgewindowssensors/bin/System.CodeDom.dll
systembridgewindowssensors/bin/System.IO.Ports.dll
systembridgewindowssensors/bin/System.Management.dll
systembridgewindowssensors/bin/SystemBridgeWindowsSensors.deps.json
systembridgewindowssensors/bin/SystemBridgeWindowsSensors.dll
systembridgewindowssensors/bin/SystemBridgeWindowsSensors.exe
systembridgewindowssensors/bin/SystemBridgeWindowsSensors.pdb
systembridgewindowssensors/bin/SystemBridgeWindowsSensors.runtimeconfig.json
systembridgewindowssensors/bin/runtimes/linux-arm/lib/netstandard2.0/Mono.Posix.NETStandard.dll
systembridgewindowssensors/bin/runtimes/linux-arm/native/libMonoPosixHelper.so
systembridgewindowssensors/bin/runtimes/linux-arm/native/libSystem.IO.Ports.Native.so
systembridgewindowssensors/bin/runtimes/linux-arm64/lib/netstandard2.0/Mono.Posix.NETStandard.dll
systembridgewindowssensors/bin/runtimes/linux-arm64/native/libMonoPosixHelper.so
systembridgewindowssensors/bin/runtimes/linux-arm64/native/libSystem.IO.Ports.Native.so
systembridgewindowssensors/bin/runtimes/linux-armel/lib/netstandard2.0/Mono.Posix.NETStandard.dll
systembridgewindowssensors/bin/runtimes/linux-armel/native/libMonoPosixHelper.so
systembridgewindowssensors/bin/runtimes/linux-x64/lib/netstandard2.0/Mono.Posix.NETStandard.dll
systembridgewindowssensors/bin/runtimes/linux-x64/native/libMonoPosixHelper.so
systembridgewindowssensors/bin/runtimes/linux-x64/native/libSystem.IO.Ports.Native.so
systembridgewindowssensors/bin/runtimes/linux-x86/lib/netstandard2.0/Mono.Posix.NETStandard.dll
systembridgewindowssensors/bin/runtimes/linux-x86/native/libMonoPosixHelper.so
systembridgewindowssensors/bin/runtimes/osx/lib/netstandard2.0/Mono.Posix.NETStandard.dll
systembridgewindowssensors-4.0.2.dist-info/LICENSE
systembridgewindowssensors-4.0.2.dist-info/METADATA
systembridgewindowssensors-4.0.2.dist-info/WHEEL
systembridgewindowssensors-4.0.2.dist-info/top_level.txt
systembridgewindowssensors-4.0.2.dist-info/RECORD
