Metadata-Version: 2.1
Name: systembridgewindowssensors
Version: 4.0.2
Summary: System Bridge Windows Sensors
Home-page: https://github.com/timmo001/system-bridge-windows-sensors
Author: Aidan Timson (Timmo)
Author-email: aidan@timmo.dev
License: Apache-2.0
Keywords: system-bridge windows
Requires-Python: >=3.11
License-File: LICENSE
Requires-Dist: incremental>=24.7.2
